{"Exif":{"Lat":0,"Long":0,"Date":"2015-01-08T16:51:17Z","Tags":{"ApertureValue":2.4000000083357924,"BitsPerSample":"8 8 8","BrightnessValue|*imagemeta.rat[int32]":"-732/6719","ComponentsConfiguration":"1 2 3 0","Compression|uint16":"1","CreateDate":"2015:01:08 16:51:17","DateTimeOriginal":"2015:01:08 16:51:17","ExposureTime|*imagemeta.rat[uint32]":"1/15","FNumber|*imagemeta.rat[uint32]":"12/5","FocalLengthIn35mmFormat|uint16":"44","FocalLength|*imagemeta.rat[uint32]":"203/100","ISO|uint16":"500","ImageHeight|uint16":"960","ImageWidth|uint16":"720","Make":"Apple","Model":"iPad 2","ModifyDate":"2017:08:02 09:36:16","Orientation|uint16":"1","PhotometricInterpretation|uint16":"2","PlanarConfiguration|uint16":"1","SamplesPerPixel|uint16":"3","SceneCaptureType|uint16":"0","SceneType|uint8":"1","ShutterSpeedValue":0.06666599848174608,"Software":"Adobe Photoshop CS3 Windows","SubSecTimeDigitized|int":"742","SubSecTimeOriginal|int":"742"}}}
